livepng/__init__.py
livepng/constants.py
livepng/exceptions.py
livepng/inspector.py
livepng/model.py
livepng/objects.py
livepng/observer.py
livepng/validator.py
livepng-0.1.7.dist-info/LICENSE.txt
livepng-0.1.7.dist-info/METADATA
livepng-0.1.7.dist-info/WHEEL
livepng-0.1.7.dist-info/top_level.txt
livepng-0.1.7.dist-info/RECORD
